Workbook

Sheet Atividades
B1: Nome do Projeto | C1: COD Projeto | D1: coluna teste | E1: Atividades Macro | F1: Tarefa | G1: Responsável pela Atividade | H1: Data da Atividade | I1: Horas Utilizadas | J1: Status | K1: Observação
B2: Perfil dos Municípios | C2: =IF(B2<>"",VLOOKUP(B2,Projetos!E:F,2,0),"") -> 2 | E2: Planejamento do Projeto | F2: Análise e Levantamento das Informações | G2: Luis Eduardo | H2: 45301 | I2: 0.25 | J2: Finalizado
B3: Relatório de Sustentabilidade - IEL | C3: =IF(B3<>"",VLOOKUP(B3,Projetos!E:F,2,0),"") -> 10 | E3: Reunião | F3: Alinhamento de Informações | G3: Sandra Marcia | H3: 45301 | I3: 0.041666667 | J3: Finalizado
B4: Relatório de Sustentabilidade - IEL | C4: =IF(B4<>"",VLOOKUP(B4,Projetos!E:F,2,0),"") -> 10 | E4: Reunião | F4: Alinhamento de Informações | G4: Ely Bastos | H4: 45301 | I4: 0.041666667 | J4: Finalizado
B5: Perfil dos Municípios | C5: =IF(B5<>"",VLOOKUP(B5,Projetos!E:F,2,0),"") -> 2 | E5: Planejamento do Projeto | F5: Análise e Levantamento das Informações | G5: Luis Eduardo | H5: 45302 | I5: 0.083333333 | J5: Finalizado
B6: Perfil dos Municípios | C6: =IF(B6<>"",VLOOKUP(B6,Projetos!E:F,2,0),"") -> 2 | E6: Planejamento do Projeto | F6: Análise e Levantamento das Informações | G6: Diego Gomes | H6: 45302 | I6: 0.083333333 | J6: Finalizado
B7: Perfil dos Municípios | C7: =IF(B7<>"",VLOOKUP(B7,Projetos!E:F,2,0),"") -> 2 | E7: Estruturação do Projeto | F7: Documentação dos indicadores | G7: Luis Eduardo | H7: 45302 | I7: 0.16666667 | J7: Finalizado
B8: Perfil dos Municípios | C8: =IF(B8<>"",VLOOKUP(B8,Projetos!E:F,2,0),"") -> 2 | E8: Estruturação do Projeto | F8: Documentação dos indicadores | G8: Diego Gomes | H8: 45302 | I8: 0.083333333 | J8: Finalizado
B9: Relatório de Sustentabilidade - IEL | C9: =IF(B9<>"",VLOOKUP(B9,Projetos!E:F,2,0),"") -> 10 | E9: Relatório | F9: Elaboração do relatório | G9: Ely Bastos | H9: 45302 | I9: 0.33333333 | J9: Finalizado
B10: Relatório de Sustentabilidade - IEL | C10: =IF(B10<>"",VLOOKUP(B10,Projetos!E:F,2,0),"") -> 10 | E10: Validação | F10: Validação | G10: Sandra Marcia | H10: 45302 | I10: 0.083333333 | J10: Finalizado
B11: Perfil dos Municípios | C11: =IF(B11<>"",VLOOKUP(B11,Projetos!E:F,2,0),"") -> 2 | E11: Extração de Dados | F11: Extração do Banco conforme Documentação | G11: Marcus Vinícius | H11: 45303 | I11: 0.25 | J11: Finalizado
B12: Relatório de Sustentabilidade - IEL | C12: =IF(B12<>"",VLOOKUP(B12,Projetos!E:F,2,0),"") -> 10 | E12: Extração de Dados | F12: Extração de informações para relatório | G12: Luis Eduardo | H12: 45303 | I12: 0.16666667 | J12: Finalizado
B13: Relatório de Sustentabilidade - IEL | C13: =IF(B13<>"",VLOOKUP(B13,Projetos!E:F,2,0),"") -> 10 | E13: Relatório | F13: Elaboração do relatório | G13: Ely Bastos | H13: 45303 | I13: 0.33333333 | J13: Finalizado
... B537: Banco de Dados Mineração | C537: =IF(B537<>"",VLOOKUP(B537,Projetos!E:F,2,0),"") -> 24 | E537: Extração de Dados | F537: Testes de extração | G537: Marcus Vinícius | H537: 45455 | I537: 0.29166667 | J537: Finalizado
B538: Livro IFC | C538: =IF(B538<>"",VLOOKUP(B538,Projetos!E:F,2,0),"") -> 13 | E538: Reunião | F538: Reunião de Alinhamentos e ajustes do projeto IFC | G538: Luis Eduardo | H538: 45456 | I538: 0.083333333 | J538: Finalizado | K538: Realizamos uma reunião para entendermos onde estavamos no projeto, devido a multiplas paradas na execução para realização de outros, nos situamos quanto ao que já tinha sido realizado, o que deveria ser alterado, além de ações futuras no projeto, discutimos prolixidades e redundancias dos textos além de formas de vizualização e disposição do conteúdo que estamos elaborando. As ações de reunião neste projeto serão constantes, visto a necessidade de alinhamento
B539: Livro IFC | C539: =IF(B539<>"",VLOOKUP(B539,Projetos!E:F,2,0),"") -> 13 | E539: Reunião | F539: Reunião de Alinhamentos e ajustes do projeto IFC | G539: Ely Bastos | H539: 45456 | I539: 0.083333333 | J539: Finalizado
B540: Livro IFC | C540: =IF(B540<>"",VLOOKUP(B540,Projetos!E:F,2,0),"") -> 13 | E540: Relatório | F540: Escrita de textos do livro IFC | G540: Luis Eduardo | H540: 45456 | I540: 0.16666667 | J540: Finalizado
B541: Painel Marketshare - Aprendiz | C541: =IF(B541<>"",VLOOKUP(B541,Projetos!E:F,2,0),"") -> 16 | E541: Painel | F541: Alteração e Ajuste | G541: Paulo Vinicius | H541: 45456 | I541: 0.16666667 | J541: Finalizado
B542: Painel Marketshare - Aprendiz | C542: =IF(B542<>"",VLOOKUP(B542,Projetos!E:F,2,0),"") -> 16 | E542: Reunião | F542: Aprovação com o Diego | G542: Paulo Vinicius | H542: 45456 | I542: 0.013888889 | J542: Finalizado
B543: Implantação Amazon | C543: =IF(B543<>"",VLOOKUP(B543,Projetos!E:F,2,0),"") -> 18 | E543: Tratamento de Dados | F543: Incluindo tabelas de Apoio | G543: Alexandre Borges | H543: 45456 | I543: 0.29166667 | J543: Finalizado
B544: Atualização Painel Mercado | C544: =IF(B544<>"",VLOOKUP(B544,Projetos!E:F,2,0),"") -> 25 | E544: Painel | F544: Ajuste na tabela d 0 E | G544: Bruno Felipe | H544: 45456 | I544: 0.083333333 | J544: Finalizado
B545: Painel Marketshare - Aprendiz | C545: =IF(B545<>"",VLOOKUP(B545,Projetos!E:F,2,0),"") -> 16 | E545: Painel | F545: Alteração e Ajuste | G545: Bruno Felipe | H545: 45456 | I545: 0.20833333 | J545: Finalizado
B546: Painel Marketshare - Aprendiz | C546: =IF(B546<>"",VLOOKUP(B546,Projetos!E:F,2,0),"") -> 16 | E546: Reunião | F546: Aprovação com o Diego | G546: Bruno Felipe | H546: 45456 | I546: 0.013888889 | J546: Finalizado
B547: Projetos e Atividades Internas | C547: =IF(B547<>"",VLOOKUP(B547,Projetos!E:F,2,0),"") -> 30 | E547: Reunião | F547: Reunião para alinhamento | G547: Marcus Vinícius | H547: 45456 | I547: 0.16666667 | J547: Finalizado
B548: Livro IFC | C548: =IF(B548<>"",VLOOKUP(B548,Projetos!E:F,2,0),"") -> 13 | E548: Estruturação do Projeto | F548: Reunião de Alinhamentos e ajustes do projeto IFC | G548: Ely Bastos | H548: 45457 | I548: 0.16666667 | J548: Finalizado
B549: Livro IFC | C549: =IF(B549<>"",VLOOKUP(B549,Projetos!E:F,2,0),"") -> 13 | E549: Relatório | F549: Escrita de textos do livro IFC | G549: Luis Eduardo | H549: 45457 | I549: 0.20833333 | J549: Finalizado
B550: Projeto Agrodefesa | C550: =IF(B550<>"",VLOOKUP(B550,Projetos!E:F,2,0),"") -> 39 | E550: Estruturação do Projeto | F550: Solicitação de Informações para definição da amostra | G550: Ely Bastos | H550: 45457 | I550: 0.083333333 | J550: Finalizado | K550: Envio par análise da Gerência e posterimente envio para o cliente.
B551: Estudos de Concorrentes RPA | C551: =IF(B551<>"",VLOOKUP(B551,Projetos!E:F,2,0),"") -> 15 | E551: Pesquisa | F551: Mapeamento dos concorrentes dos clientes RPA | G551: Paulo Vinicius | H551: 45457 | I551: 0.19097222 | J551: Finalizado
B552: Iniciativas de Mercados - CMs | C552: 27 | E552: Reunião | F552: planejamento de execução de cada um dos CMs | G552: Paulo Vinicius | H552: 45457 | I552: 0.059027778 | J552: Finalizado
B553: Iniciativas de Mercados - CMs | C553: =IF(B553<>"",VLOOKUP(B553,Projetos!E:F,2,0),"") -> 27 | E553: Reunião | F553: planejamento de execução de cada um dos CMs | G553: Bruno Felipe | H553: 45457 | I553: 0.059027778 | J553: Finalizado
B554: Atualização Painel Mercado | C554: =IF(B554<>"",VLOOKUP(B554,Projetos!E:F,2,0),"") -> 25 | E554: Alteração/Ajustes | F554: Ajustes na tabela entregue, vendido e na aba Analytics | G554: Bruno Felipe | H554: 45457 | I554: 0.125 | J554: Finalizado
B555: Implantação Amazon | C555: =IF(B555<>"",VLOOKUP(B555,Projetos!E:F,2,0),"") -> 18 | E555: Tratamento de Dados | F555: Inserindo tabelas de Apoio (Municipio, CNAE, CBO, CID) | G555: Alexandre Borges | H555: 45457 | I555: 0.29166667 | J555: Finalizado
B556: Atualização Painel Saúde | C556: =IF(B556<>"",VLOOKUP(B556,Projetos!E:F,2,0),"") -> 22 | E556: Tratamento de Dados | F556: Estudos da Base com desenvolvimento dos indicadores | G556: Rodolfo Viscal | H556: 45457 | I556: 0.33333333 | J556: Finalizado | K556: Problemas de conflitos com bases não conversando uma com a outra
B557: Projetos e Atividades Internas | C557: =IF(B557<>"",VLOOKUP(B557,Projetos!E:F,2,0),"") -> 30 | E557: Proposta / Contrato | F557: Estruturação da Proposta Unimed Cerrado | G557: Diego Gomes | H557: 45457 | I557: 0.29166667 | J557: Finalizado
B558: Banco de Dados Mineração | C558: =IF(B558<>"",VLOOKUP(B558,Projetos!E:F,2,0),"") -> 24 | E558: Alteração/Ajustes | F558: Alteração nos scripts e novos testes | G558: Marcus Vinícius | H558: 45457 | I558: 0.25 | J558: Finalizado
B559: Atualização Painel Saúde | C559: =IF(B559<>"",VLOOKUP(B559,Projetos!E:F,2,0),"") -> 22 | E559: Tratamento de Dados | F559: Estudos da Base com desenvolvimento dos indicadores | G559: Rodolfo Viscal | H559: 45458 | I559: 0.33333333 | J559: Finalizado
B560: Livro IFC | C560: =IF(B560<>"",VLOOKUP(B560,Projetos!E:F,2,0),"") -> 13 | E560: Relatório | F560: Escrita de textos do livro IFC | G560: Luis Eduardo | H560: 45460 | I560: 0.16666667 | J560: Finalizado
B561: PDE - Serra Verde | C561: =IF(B561<>"",VLOOKUP(B561,Projetos!E:F,2,0),"") -> 3 | E561: Reunião | F561: Reunião sobre manual PDE | G561: Luis Eduardo | H561: 45460 | I561: 0.083333333 | J561: Finalizado
B562: Estudos de Concorrentes RPA | C562: =IF(B562<>"",VLOOKUP(B562,Projetos!E:F,2,0),"") -> 15 | E562: Coleta | F562: Lista de prospecção | G562: Paulo Vinicius | H562: 45460 | I562: 0.25 | J562: Finalizado
B563: Painel de Gestão | C563: =IF(B563<>"",VLOOKUP(B563,Projetos!E:F,2,0),"") -> 23 | E563: Painel | F563: atividades do colaboradores com a base | G563: Rodolfo Viscal | H563: 45460 | I563: 0.33333333 | J563: Finalizado
B564: Implantação Amazon | C564: =IF(B564<>"",VLOOKUP(B564,Projetos!E:F,2,0),"") -> 18 | E564: Tratamento de Dados | F564: Criando Views do CAGED para alimentar PowerBI | G564: Alexandre Borges | H564: 45460 | I564: 0.29166667 | J564: Finalizado
B565: Estudos de Concorrentes RPA | C565: =IF(B565<>"",VLOOKUP(B565,Projetos!E:F,2,0),"") -> 15 | E565: Coleta | F565: Lista de prospecção | G565: Bruno Felipe | H565: 45460 | I565: 0.25 | J565: Parado
B566: Atualização Painel Mercado | C566: =IF(B566<>"",VLOOKUP(B566,Projetos!E:F,2,0),"") -> 25 | E566: Alteração/Ajustes | F566: Problemas na tabela A 1 F durante a atualização diária | G566: Bruno Felipe | H566: 45460 | I566: 0.083333333 | J566: Finalizado
B567: Projetos e Atividades Internas | C567: =IF(B567<>"",VLOOKUP(B567,Projetos!E:F,2,0),"") -> 30 | E567: Reunião | F567: Reunião de apresentação da Proposta Unimed | G567: Diego Gomes | H567: 45460 | I567: 0.083333333 | J567: Finalizado
B568: Projetos e Atividades Internas | C568: =IF(B568<>"",VLOOKUP(B568,Projetos!E:F,2,0),"") -> 30 | E568: Proposta / Contrato | F568: Correção e Ajustes na Proposta Unimed | G568: Diego Gomes | H568: 45460 | I568: 0.20833333 | J568: Finalizado
... B591: Marketshare Estágio | C591: =IF(B591<>"",VLOOKUP(B591,Projetos!E:F,2,0),"") -> 14 | E591: Extração de Dados | F591: Extrair informações do SNE referente a idade, n° tce, data de inicio e termino de 2021 ate a data atual | G591: Alexandre Borges | H591: 45462 | I591: 0.083333333 | J591: Finalizado
B592: Projetos e Atividades Internas | C592: =IF(B592<>"",VLOOKUP(B592,Projetos!E:F,2,0),"") -> 30 | E592: Extração de Dados | F592: Extração de informações de Admitidos e Desligados por UF e média salarial dos admitidos por uf | G592: Alexandre Borges | H592: 45462 | I592: 0.20833333 | J592: Finalizado | K592: Tempo elevado devido a complexidade em extrair alguns dados. Proximas demandas deverão ser mais rapidas pois os scripts já estão pre moldados.
B593: Painel Marketshare - Aprendiz | C593: =IF(B593<>"",VLOOKUP(B593,Projetos!E:F,2,0),"") -> 16 | E593: Painel | F593: Reavaliação do painel | G593: Paulo Vinicius | H593: 45462 | I593: 0.0625 | J593: Finalizado
B594: Marketshare Estágio | C594: =IF(B594<>"",VLOOKUP(B594,Projetos!E:F,2,0),"") -> 14 | E594: Painel | F594: Reavaliação dos cálculos | G594: Paulo Vinicius | H594: 45462 | I594: 0.1875 | J594: Finalizado
B595: Banco de Dados Mineração | C595: =IF(B595<>"",VLOOKUP(B595,Projetos!E:F,2,0),"") -> 24 | E595: Extração de Dados | F595: Testes e validação dos dados | G595: Marcus Vinícius | H595: 45462 | I595: 0.47222222 | J595: Finalizado
B596: Painel de Gestão | C596: =IF(B596<>"",VLOOKUP(B596,Projetos!E:F,2,0),"") -> 23 | E596: Estruturação do Projeto | F596: Correção e Adição de atividades do projeto | G596: Diego Gomes | H596: 45462 | I596: 0.125 | J596: Finalizado
B597: Projetos e Atividades Internas | C597: =IF(B597<>"",VLOOKUP(B597,Projetos!E:F,2,0),"") -> 30 | E597: Estruturação do Projeto | F597: Correções e ajustes nas propostas Hospitais | G597: Diego Gomes | H597: 45462 | I597: 0.125 | J597: Finalizado
B598: PDE - Serra Verde | C598: =IF(B598<>"",VLOOKUP(B598,Projetos!E:F,2,0),"") -> 3 | E598: Alteração/Ajustes | F598: Alteração de formatos de arquivos da Serra Verde, alinhamento de materiais e conteudos para o projeto | G598: Luis Eduardo | H598: 45462 | I598: 0.25 | J598: Finalizado
B599: Painel de Gestão | C599: =IF(B599<>"",VLOOKUP(B599,Projetos!E:F,2,0),"") -> 23 | E599: Painel | F599: Continuação da Pagina de Colaboradores | G599: Rodolfo Viscal | H599: 45463 | I599: 0.25 | J599: Finalizado
B600: Projetos e Atividades Internas | C600: =IF(B600<>"",VLOOKUP(B600,Projetos!E:F,2,0),"") -> 30 | E600: Extração de Dados | F600: Configurando consultas de extração de Admitidos e Desligados do CAGED | G600: Alexandre Borges | H600: 45463 | I600: 0.083333333 | J600: Finalizado
B601: Implantação Amazon | C601: =IF(B601<>"",VLOOKUP(B601,Projetos!E:F,2,0),"") -> 18 | E601: Painel | F601: Teste de conexão com DirectQuery | G601: Rodolfo Viscal | H601: 45463 | I601: 0.25 | J601: Finalizado
B602: Treinamentos e Capacitações | C602: =IF(B602<>"",VLOOKUP(B602,Projetos!E:F,2,0),"") -> 32 | E602: Capacitação | F602: AI-900:Microsoft Azure AI Fundamentals | G602: Alexandre Borges | H602: 45463 | I602: 0.041666667 | J602: Finalizado
B603: Painel Institucional - Superintendência | C603: 33 | E603: Alteração/Ajustes | F603: Alteração de código para o ano de 2024 e de fonte | G603: Bruno Felipe | H603: 45463 | I603: 0.125 | J603: Finalizado
B604: Atualização Painel Mercado | C604: =IF(B604<>"",VLOOKUP(B604,Projetos!E:F,2,0),"") -> 25 | E604: Atualização | F604: Ajustando valores do funil entregue antes de atualizar | G604: Bruno Felipe | H604: 45463 | I604: 0.125 | J604: Finalizado
B605: Painel Marketshare - Estágio | C605: =IF(B605<>"",VLOOKUP(B605,Projetos!E:F,2,0),"") -> 17 | E605: Tratamento de Dados | F605: Reavaliação dos cálculos da estimativa | G605: Paulo Vinicius | H605: 45463 | I605: 0.083333333 | J605: Finalizado
B606: Painel de Gestão | C606: =IF(B606<>"",VLOOKUP(B606,Projetos!E:F,2,0),"") -> 23 | E606: Estruturação do Projeto | F606: Correção e Adição de atividades do projeto | G606: Diego Gomes | H606: 45463 | I606: 0.125 | J606: Finalizado
B607: Projetos e Atividades Internas | C607: =IF(B607<>"",VLOOKUP(B607,Projetos!E:F,2,0),"") -> 30 | E607: Reunião | F607: Alinhamento de Atividades | G607: Diego Gomes | H607: 45463 | I607: 0.041666667 | J607: Finalizado
B608: Projetos e Atividades Internas | C608: =IF(B608<>"",VLOOKUP(B608,Projetos!E:F,2,0),"") -> 30 | E608: Estruturação do Projeto | F608: Ajuste e Validação da Proposta Redehemo | G608: Diego Gomes | H608: 45463 | I608: 0.125 | J608: Finalizado
B609: PDE - Serra Verde | C609: =IF(B609<>"",VLOOKUP(B609,Projetos!E:F,2,0),"") -> 3 | E609: Alteração/Ajustes | F609: Alteração de formatos de arquivos da Serra Verde, alinhamento de materiais e conteudos para o projeto | G609: Luis Eduardo | H609: 45463 | I609: 0.25 | J609: Finalizado
B610: Implantação Amazon | C610: =IF(B610<>"",VLOOKUP(B610,Projetos!E:F,2,0),"") -> 18 | E610: Tratamento de Dados | F610: Criando Fluxo para ativação dos scripts de extração da ANM | G610: Marcus Vinícius | H610: 45463 | I610: 0.125 | J610: Finalizado
B611: Projetos e Atividades Internas | C611: =IF(B611<>"",VLOOKUP(B611,Projetos!E:F,2,0),"") -> 30 | E611: Reunião | F611: Analisando detalhes para divulgação da atualização do PIM-PF Mensal | G611: Marcus Vinícius | H611: 45463 | I611: 0.083333333 | J611: Finalizado
B612: Banco de Dados Mineração | C612: =IF(B612<>"",VLOOKUP(B612,Projetos!E:F,2,0),"") -> 24 | E612: Extração de Dados | F612: Manutenção dos scripts que ocorreram erros | G612: Marcus Vinícius | H612: 45463 | I612: 0.16666667 | J612: Finalizado
B613: Implantação Amazon | C613: =IF(B613<>"",VLOOKUP(B613,Projetos!E:F,2,0),"") -> 18 | E613: Tratamento de Dados | F613: Criando tabelas de de apoio no banco refined | G613: Alexandre Borges | H613: 45464 | I613: 0.16666667 | J613: Finalizado
B614: Pré-projeto Monitora Linkedin | C614: =IF(B614<>"",VLOOKUP(B614,Projetos!E:F,2,0),"") -> 34 | E614: Estruturação do Projeto | F614: Estruturação | G614: Paulo Vinicius | H614: 45464 | I614: 0.125 | J614: Finalizado
B615: PDE - Serra Verde | C615: =IF(B615<>"",VLOOKUP(B615,Projetos!E:F,2,0),"") -> 3 | E615: Alteração/Ajustes | F615: Alteração de formatos de arquivos da Serra Verde, alinhamento de materiais e conteudos para o projeto | G615: Luis Eduardo | H615: 45464 | I615: 0.25 | J615: Finalizado
... B640: Atualização Painel Saúde | C640: =IF(B640<>"",VLOOKUP(B640,Projetos!E:F,2,0),"") -> 22 | E640: Painel | F640: desenvolvimento de visuais ecalculos | G640: Rodolfo Viscal | H640: 45468 | I640: 0.083333333 | J640: Finalizado
B641: Banco de Dados Mineração | C641: 24 | E641: Extração de Dados | F641: Testes de extração e validação dos dados | G641: Marcus Vinícius | H641: 45468 | I641: 0.27083333 | J641: Finalizado
B642: Painel de Gestão | C642: 23 | E642: Alteração/Ajustes | F642: Análise do painel para fazer ajustes para a entrega final | G642: Isadora Pereira | H642: 45468 | I642: 0.083333333 | J642: Finalizado
B643: Projetos e Atividades Internas | C643: =IF(B643<>"",VLOOKUP(B643,Projetos!E:F,2,0),"") -> 30 | E643: Extração de Dados | F643: Tratamento de dados da Indústria de Quirinópolis na base da Receita Federal e de Goiás do CAGED e RAIS | G643: Diego Gomes | H643: 45468 | I643: 0.16666667 | J643: Finalizado
B644: Painel de Gestão | C644: =IF(B644<>"",VLOOKUP(B644,Projetos!E:F,2,0),"") -> 23 | E644: Alteração/Ajustes | F644: Ajustes e correções da planilha para os colaboradores | G644: Diego Gomes | H644: 45468 | I644: 0.041666667 | J644: Finalizado
B645: PDE - Serra Verde | C645: =IF(B645<>"",VLOOKUP(B645,Projetos!E:F,2,0),"") -> 3 | E645: Alteração/Ajustes | F645: Ajustes formato dos relatórios | G645: Luis Eduardo | H645: 45468 | I645: 0.25 | J645: Finalizado
B646: Painel Utilidades - Mercado | C646: =IF(B646<>"",VLOOKUP(B646,Projetos!E:F,2,0),"") -> 35 | E646: Alteração/Ajustes | F646: medidas | G646: Bruno Felipe | H646: 45468 | I646: 0.125 | J646: Finalizado
B647: Pré-projeto Monitora Linkedin | C647: =IF(B647<>"",VLOOKUP(B647,Projetos!E:F,2,0),"") -> 34 | E647: Estruturação do Projeto | F647: Reavaliação do projeto para excel | G647: Bruno Felipe | H647: 45468 | I647: 0.020833333 | J647: Finalizado
B648: Atualização Painel Mercado | C648: =IF(B648<>"",VLOOKUP(B648,Projetos!E:F,2,0),"") -> 25 | E648: Painel | F648: Atualização | G648: Bruno Felipe | H648: 45468 | I648: 0.0069444444 | J648: Finalizado
B649: Pré-projeto Monitora Linkedin | C649: =IF(B649<>"",VLOOKUP(B649,Projetos!E:F,2,0),"") -> 34 | E649: Extração de Dados | F649: Extraindo informação da rede e analisando para o relatório | G649: Paulo Vinicius | H649: 45468 | I649: 0.14583333 | J649: Finalizado
B650: Painel Marketshare - Aprendiz | C650: =IF(B650<>"",VLOOKUP(B650,Projetos!E:F,2,0),"") -> 16 | E650: Alteração/Ajustes | F650: Reavaliação do visual | G650: Paulo Vinicius | H650: 45468 | I650: 0.041666667 | J650: Finalizado
B651: Banco de Dados Mineração | C651: =IF(B651<>"",VLOOKUP(B651,Projetos!E:F,2,0),"") -> 24 | E651: Alteração/Ajustes | F651: Testes e correções das pipelines de extração | G651: Marcus Vinícius | H651: 45469 | I651: 0.25 | J651: Finalizado
B652: PDE - Serra Verde | C652: =IF(B652<>"",VLOOKUP(B652,Projetos!E:F,2,0),"") -> 3 | E652: Reunião | F652: Reunião com os Gestores para definição das novas ações | G652: Fernanda Heleno | H652: 45469 | I652: 0.16666667 | J652: Finalizado
B653: PDE - Serra Verde | C653: =IF(B653<>"",VLOOKUP(B653,Projetos!E:F,2,0),"") -> 3 | E653: Coleta | F653: Coleta de informações nas entrevistas com o pessoal | G653: Fernanda Heleno | H653: 45469 | I653: 0.16666667 | J653: Finalizado
B654: Projetos e Atividades Internas | C654: =IF(B654<>"",VLOOKUP(B654,Projetos!E:F,2,0),"") -> 30 | E654: Atualização | F654: Estudos de Novos Visuais, da Nova atualização Power Bi | G654: Rodolfo Viscal | H654: 45469 | I654: 0.125 | J654: Finalizado
... B656: PDE - Serra Verde | C656: =IF(B656<>"",VLOOKUP(B656,Projetos!E:F,2,0),"") -> 3 | E656: Alteração/Ajustes | F656: Ajustes formato dos relatórios | G656: Luis Eduardo | H656: 45469 | I656: 0.25 | J656: Finalizado
B657: Painel Marketshare - Aprendiz | C657: 16 | E657: Alteração/Ajustes | F657: Reavaliação do visual | G657: Paulo Vinicius | H657: 45469 | I657: 0.125 | J657: Finalizado
B658: Pré-projeto Monitora Linkedin | C658: =IF(B658<>"",VLOOKUP(B658,Projetos!E:F,2,0),"") -> 34 | E658: Relatório | F658: Extração dos dados e elaboração do projeto | G658: Paulo Vinicius | H658: 45469 | I658: 0.125 | J658: Finalizado
B659: Painel Marketshare - Aprendiz | C659: =IF(B659<>"",VLOOKUP(B659,Projetos!E:F,2,0),"") -> 16 | E659: Painel | F659: Revaliação visual | G659: Bruno Felipe | H659: 45469 | I659: 0.020833333 | J659: Finalizado
B660: Atualização Painel Mercado | C660: =IF(B660<>"",VLOOKUP(B660,Projetos!E:F,2,0),"") -> 25 | E660: Alteração/Ajustes | F660: Nome em "branco" na coluna produto do funil venda no painel mercado | G660: Bruno Felipe | H660: 45469 | I660: 0.125 | J660: Finalizado
B661: Pré-projeto Monitora Linkedin | C661: =IF(B661<>"",VLOOKUP(B661,Projetos!E:F,2,0),"") -> 34 | E661: Relatório | F661: Extraindo informação da rede e analisando para o relatório | G661: Bruno Felipe | H661: 45469 | I661: 0.10416667 | J661: Finalizado
B662: Treinamentos e Capacitações | C662: =IF(B662<>"",VLOOKUP(B662,Projetos!E:F,2,0),"") -> 32 | E662: Capacitação | F662: Estudo do Projeto de Descarbonização da Minerção | G662: Diego Gomes | H662: 45469 | I662: 0.16666667 | J662: Finalizado
B663: Painel de Gestão | C663: =IF(B663<>"",VLOOKUP(B663,Projetos!E:F,2,0),"") -> 23 | E663: Alteração/Ajustes | F663: Ajustes e correções da planilha para os colaboradores | G663: Diego Gomes | H663: 45469 | I663: 0.041666667 | J663: Finalizado
B664: Implantação Amazon | C664: =IF(B664<>"",VLOOKUP(B664,Projetos!E:F,2,0),"") -> 18 | E664: Extração de Dados | F664: Acompanhando equipe da Amazon na solução de situações problema reportadas por mim | G664: Alexandre Borges | H664: 45469 | I664: 0.29166667 | J664: Finalizado
B665: PDE - Serra Verde | C665: =IF(B665<>"",VLOOKUP(B665,Projetos!E:F,2,0),"") -> 3 | E665: Reunião | F665: Reunião com os Gestores para definição das novas ações | G665: Fernanda Heleno | H665: 45470 | I665: 0.16666667 | J665: Finalizado
B666: PDE - Serra Verde | C666: =IF(B666<>"",VLOOKUP(B666,Projetos!E:F,2,0),"") -> 3 | E666: Coleta | F666: Coleta de informações nas entrevistas com o pessoal | G666: Fernanda Heleno | H666: 45470 | I666: 0.16666667 | J666: Finalizado
B667: Atualização Painel Saúde | C667: =IF(B667<>"",VLOOKUP(B667,Projetos!E:F,2,0),"") -> 22 | E667: Painel | F667: Desenvolvimento da pagina de leitos | G667: Rodolfo Viscal | H667: 45470 | I667: 0.29166667 | J667: Finalizado
B668: Banco de Dados Mineração | C668: =IF(B668<>"",VLOOKUP(B668,Projetos!E:F,2,0),"") -> 24 | E668: Extração de Dados | F668: Validação dos dados e correções da pipeline de extração / Documentação do banco de dados | G668: Marcus Vinícius | H668: 45470 | I668: 0.29166667 | J668: Finalizado
B669: Implantação Amazon | C669: =IF(B669<>"",VLOOKUP(B669,Projetos!E:F,2,0),"") -> 18 | E669: Tratamento de Dados | F669: Testes de conexão com Power Bi Service | G669: Rodolfo Viscal | H669: 45470 | I669: 0.041666667 | J669: Finalizado
... B718: Atualização Painel Mercado | C718: =IF(B718<>"",VLOOKUP(B718,Projetos!E:F,2,0),"") -> 25 | E718: Alteração/Ajustes | F718: Criação de medida - meta e alteração no na home da página | G718: Bruno Felipe | H718: 45474 | I718: 0.1875 | J718: Finalizado
...

Sheet Projetos
A2: Cod Área | B2: Área Observatório | C2: Área | D2: Líder do Projeto | E2: Nome do Projeto | F2: Cod Projeto | G2: Lista do Projeto | H2: Data Início do Projeto | I2: Data Término do Projeto | J2: Total de Horas | K2: Status | L2: Total do Projeto (R$) | M2: Realizado (R$) | N2: Fonte de Recursos | O2: Classe | P2: Cliente Final
A3: 1 | B3: Observatorio | C3: Inteligência de Dados | D3: Diego Gomes | E3: Atualização de Painel - Educação | F3: 1 | H3: 45402 | I3: 45427 | J3: 108 | K3: Finalizado | L3: 3780 | N3: Institucional | O3: Atualização | P3: OBSERVATORIO
A4: 1 | B4: Observatorio | C4: Inteligência de Dados | D4: Diego Gomes | E4: Perfil dos Municípios | F4: 2 | G4: Perfil_dos_Municípios | H4: 45301 | I4: 45382 | J4: 528 | K4: Em andamento | L4: 18480 | N4: Institucional | O4: Atualização | P4: OBSERVATORIO
A5: 1 | B5: Observatorio | C5: Inteligência Competitiva | D5: Ely Bastos | E5: PDE - Serra Verde | F5: 3 | G5: PDE_Serra_Verde | H5: 45432 | I5: 45443 | J5: 480 | K5: Em andamento | L5: 20000 | N5: Institucional | O5: Pesquisa | P5: IEL - PDF
A6: 1 | B6: Observatorio | C6: Inteligência de Dados | D6: Diego Gomes | E6: Atualização da Base de Dados FIEG | F6: 4 | H6: 45343 | I6: 45348 | J6: 8 | K6: Finalizado | L6: 520 | N6: Institucional | O6: Atualização | P6: FIEG
A7: 1 | B7: Observatorio | C7: Inteligência de Dados | D7: Diego Gomes | E7: Validação Lista de Empresas - DAIA | F7: 5 | H7: 45330 | I7: 45338 | J7: 6 | K7: Finalizado | L7: 390 | N7: Institucional | O7: Banco de Dados | P7: SINDICATOS
A8: 1 | B8: Observatorio | C8: Inteligência de Dados | D8: Diego Gomes | E8: Relatório Rotatividade Farmoquímico | F8: 6 | H8: 45336 | I8: 45338 | J8: 11 | K8: Finalizado | L8: 715 | N8: Institucional | O8: Banco de Dados | P8: SINDICATOS
A9: 1 | B9: Observatorio | C9: Inteligência de Dados | D9: Diego Gomes | E9: Relatório Sindmóveis | F9: 7 | H9: 45331 | I9: 45337 | J9: 5 | K9: Finalizado | L9: 325 | N9: Institucional | O9: Banco de Dados | P9: SINDICATOS
A10: 1 | B10: Observatorio | C10: Inteligência de Dados | D10: Diego Gomes | E10: Lista de Empresas Confecção | F10: 8 | H10: 45340 | I10: 45341 | J10: 5 | K10: Finalizado | L10: 325 | N10: Institucional | O10: Banco de Dados | P10: SINDICATOS
A11: 1 | B11: Observatorio | C11: Inteligência de Dados | D11: Diego Gomes | E11: Apresentação Descarbonização da Mineração | F11: 9 | H11: 45313 | I11: 45345 | J11: 37 | K11: Finalizado | L11: 2405 | N11: Institucional | O11: Banco de Dados | P11: FIEG
A12: 1 | B12: Observatorio | C12: Inteligência Competitiva | D12: Ely Bastos | E12: Relatório de Sustentabilidade - IEL | F12: 10 | H12: 45301 | I12: 45427 | J12: 596 | K12: Finalizado | L12: 32780 | N12: Institucional | O12: Banco de Dados | P12: IEL - MERCADO
A13: 1 | B13: Observatorio | C13: Inteligência de Dados | D13: Diego Gomes | E13: Atualização e Melhoria do IFC | F13: 11 | H13: 45313 | I13: 45387 | J13: 264 | K13: Finalizado | L13: 9240 | N13: Institucional | O13: Banco de Dados | P13: IEL - SUPERINTENDÊNCIA
A14: 1 | B14: Observatorio | C14: Inteligência de Mercado | D14: Bruno Felipe | E14: Estudo de Microregiões - Ceres | F14: 12 | H14: 45369 | I14: 45380 | J14: 129 | K14: Finalizado | L14: 4515 | N14: Institucional | O14: Estudo | P14: IEL - MERCADO
A15: 1 | B15: Observatorio | C15: Inteligência Competitiva | D15: Ely Bastos | E15: Livro IFC | F15: 13 | H15: 45371 | I15: 45402 | J15: 331 | K15: Finalizado | L15: 18205 | N15: Institucional | O15: Estudo | P15: OBSERVATORIO
A16: 1 | B16: Observatorio | C16: Inteligência de Mercado | D16: Bruno Felipe | E16: Marketshare Estágio | F16: 14 | H16: 45377 | I16: 45439 | J16: 80 | K16: Finalizado | L16: 2800 | N16: Institucional | O16: Pesquisa | P16: IEL - MERCADO
A17: 1 | B17: Observatorio | C17: Inteligência de Mercado | D17: Bruno Felipe | E17: Estudos de Concorrentes RPA | F17: 15 | H17: 45390 | I17: 45471 | J17: 149 | K17: Parado | L17: 5215 | N17: Institucional | O17: Pesquisa | P17: IEL - MERCADO
... A19: 1 | B19: Observatorio | C19: Inteligência de Mercado | D19: Bruno Felipe | E19: Painel Marketshare - Estágio | F19: 17 | H19: 45377 | I19: 45439 | J19: 90 | K19: Finalizado | L19: 700 | N19: Institucional | O19: Atualização | P19: OBSERVATORIO
A20: 1 | B20: Observatorio | C20: Inteligência de Dados | D20: Alexandre Borges | E20: Implantação Amazon | F20: 18 | G20: Implantação_Amazon | H20: 45383 | I20: 45534 | J20: 300 | K20: Em andamento | L20: 18000 | N20: Institucional | O20: Atualização | P20: OBSERVATORIO
A21: 1 | B21: Observatorio | C21: Inteligência de Dados | D21: Alexandre Borges | E21: MTE - CAGED | F21: 19 | G21: MTE_CAGED | H21: 45292 | I21: 45657 | J21: 90 | K21: Em andamento | L21: 5850 | N21: Institucional | O21: Banco de Dados | P21: OBSERVATORIO
A22: 1 | B22: Observatorio | C22: Inteligência de Dados | D22: Alexandre Borges | E22: MTE - RAIS | F22: 20 | H22: 45292 | I22: 45657 | J22: 45 | K22: Em andamento | L22: 2475 | N22: Institucional | O22: Banco de Dados | P22: OBSERVATORIO
A23: 1 | B23: Observatorio | C23: Inteligência de Dados | D23: Marcus Vinícius | E23: Panorama Econômico | F23: 21 | G23: Panorama_Econômico | H23: 45292 | I23: 45657 | J23: 264 | K23: Em andamento | L23: 14520 | N23: Institucional | O23: Banco de Dados | P23: OBSERVATORIO
A24: 1 | B24: Observatorio | C24: Inteligência de Dados | D24: Rodolfo Viscal | E24: Atualização Painel Saúde | F24: 22 | H24: 45413 | I24: 45504 | J24: 700 | K24: Finalizado | L24: 31500 | N24: Institucional | O24: Atualização | P24: OBSERVATORIO
A25: 1 | B25: Observatorio | C25: Gestão | D25: Rodolfo Viscal | E25: Painel de Gestão | F25: 23 | G25: Painel_de_Gestão | H25: 45446 | I25: 45504 | J25: 250 | K25: Em andamento | L25: 12500 | N25: Institucional | O25: Painel | P25: OBSERVATORIO
A26: 1 | B26: Observatorio | C26: Inteligência de Dados | D26: Marcus Vinícius | E26: Banco de Dados Mineração | F26: 24 | G26: Banco_de_Dados_Mineração | H26: 45453 | I26: 45504 | J26: 106 | K26: Em andamento | L26: 5830 | N26: Institucional | O26: Banco de Dados | P26: OBSERVATORIO
A27: 1 | B27: Observatorio | C27: Inteligência de Mercado | D27: Bruno Felipe | E27: Atualização Painel Mercado | F27: 25 | G27: Atualização_Painel_Mercado | H27: 45446 | I27: 45657 | J27: 118 | K27: Em andamento | L27: 5310 | N27: Institucional | O27: Painel | P27: IEL - MERCADO
A28: 1 | B28: Observatorio | C28: Inteligência Competitiva | D28: Ely Bastos | E28: Diagnóstico dos Produtores da Agrodefesa | F28: 26 | H28: 45456 | I28: 45657 | J28: 100 | K28: Parado | L28: 5500 | N28: Mercado | O28: Estudo | P28: MERCADO
A29: 1 | B29: Observatorio | C29: Inteligência de Mercado | D29: Bruno Felipe | E29: Iniciativas de Mercados - CMs | F29: 27 | G29: Iniciativas_de_Mercados_CMs | H29: 45453 | I29: 45657 | J29: 120 | K29: Em andamento | L29: 5400 | N29: Institucional | O29: Estudo | P29: IEL - MERCADO
A30: 1 | B30: Observatorio | C30: Inteligência de Mercado | D30: Bruno Felipe | E30: Painel de Clientes | F30: 28 | H30: 45413 | I30: 45504 | J30: 80 | K30: Finalizado | L30: 2800 | N30: Institucional | O30: Painel | P30: IEL - MERCADO
A31: 1 | B31: Observatorio | C31: Inteligência de Mercado | D31: Bruno Felipe | E31: Newsletter PIM-PF | F31: 29 | H31: 45413 | I31: 45657 | J31: 60 | K31: Finalizado | L31: 2100 | N31: Institucional | O31: Estudo | P31: OBSERVATORIO
A32: 1 | B32: Observatorio | C32: Inteligência de Dados | D32: Diego Gomes | E32: Projetos e Atividades Internas | F32: 30 | G32: Projetos_e_Atividades_Internas | H32: 45292 | I32: 45657 | J32: 300 | K32: Em andamento | L32: 16500 | N32: Institucional | O32: Estudo | P32: OBSERVATORIO
A33: 1 | B33: Observatorio | C33: Gestão | D33: Diego Gomes | E33: Observatório Nacional | F33: 31 | G33: Observatório_Nacional | H33: 45444 | I33: 45657 | J33: 300 | K33: Em andamento | L33: 16500 | N33: Institucional | O33: Planejamento | P33: OBSERVATORIO
A34: 1 | B34: Observatorio | C34: Inteligência de Dados | D34: Diego Gomes | E34: Treinamentos e Capacitações | F34: 32 | G34: Treinamentos_e_Capacitações | H34: 45444 | I34: 45657 | J34: 400 | K34: Em andamento | L34: 26000 | N34: Institucional | O34: Planejamento | P34: OBSERVATORIO
A35: 1 | B35: Observatorio | C35: Inteligência de Mercado | D35: Bruno Felipe | E35: Painel Institucional - Superintendência | F35: 33 | G35: Painel_Institucional_Superintendência | H35: 45444 | I35: 45657 | J35: 300 | K35: Em andamento | L35: 16500 | N35: Institucional | O35: Planejamento | P35: IEL - SUPERINTENDÊNCIA
A36: 1 | B36: Observatorio | C36: Inteligência de Mercado | D36: Bruno Felipe | E36: Pré-projeto Monitora Linkedin | F36: 34 | H36: 45468 | I36: 45469 | J36: 28 | K36: Finalizado | L36: 980 | N36: Institucional | O36: Painel | P36: IEL - MERCADO
A37: 1 | B37: Observatorio | C37: Inteligência de Mercado | D37: Bruno Felipe | E37: Painel Utilidades - Mercado | F37: 35 | G37: Painel_Utilidades_Mercado | H37: 45444 | I37: 45657 | J37: 300 | K37: Em andamento | L37: 16500 | N37: Institucional | O37: Painel | P37: IEL - MERCADO
A38: 1 | B38: Observatorio | C38: Gestão | D38: Isadora Pereira | E38: Gestão do Conhecimento | F38: 36 | G38: Gestão_do_Conhecimento | H38: 45352 | I38: 45657 | J38: 80 | K38: Em andamento | L38: 2000 | N38: Institucional | O38: Planejamento | P38: OBSERVATORIO
A39: 1 | B39: Observatorio | C39: Gestão | D39: Isadora Pereira | E39: Gestão de Portfólio | F39: 37 | G39: Gestão_de_Portfólio | H39: 45292 | I39: 45657 | J39: 80 | K39: Em andamento | L39: 2001 | N39: Institucional | O39: Planejamento | P39: OBSERVATORIO
A40: 1 | B40: Observatorio | C40: Inteligência de Dados | D40: Paulo Vinicius | E40: Relatório Município de Nova Roma | F40: 38 | H40: 45471 | I40: 45474 | J40: 7 | K40: Finalizado | L40: 245 | N40: Institucional | O40: Banco de Dados | P40: SESI
A41: 1 | B41: Observatorio | C41: Inteligência Competitiva | D41: Ely Bastos | E41: Projeto Agrodefesa | F41: 39 | G41: Projeto_Agrodefesa | H41: 45444 | I41: 45657 | J41: 600 | K41: Em andamento | L41: 105033.5 | N41: Mercado | O41: Pesquisa | P41: MERCADO
A42: 1 | B42: Observatorio | C42: Inteligência de Mercado | D42: Paulo Vinicius | E42: Painel Aprendizagem - SENAI | F42: 40 | G42: Painel_Aprendizagem_SENAI | H42: 45474 | I42: 45657 | J42: 100 | K42: Em andamento | L42: 3500 | N42: Institucional | O42: Painel | P42: IEL - MERCADO
A43: 1 | B43: Observatorio | C43: Inteligência de Dados | D43: Sandra Marcia | E43: Painel Sinduscon | F43: 41 | G43: Painel_Sinduscon | H43: 45505 | I43: 45657 | J43: 100 | K43: Não Iniciado | L43: 0 | N43: Institucional | O43: Painel | P43: SINDICATOS
A44: 1 | B44: Observatorio | C44: Inteligência de Dados | D44: Sandra Marcia | E44: Bússola da Inovação | F44: 42 | G44: Bússola_da_Inovação | H44: 45505 | I44: 45657 | J44: 300 | K44: Não Iniciado | L44: 0 | N44: Institucional | O44: Estudo | P44: OBSERVATORIO
A45: 1 | B45: Observatorio | C45: Inteligência de Dados | D45: Sandra Marcia | E45: Melhoria Diagnóstivo de Inovação | F45: 43 | G45: Melhoria_Diagnóstivo_de_Inovação | H45: 45505 | I45: 45657 | J45: 100 | K45: Não Iniciado | L45: 0 | N45: Institucional | O45: Atualização | P45: OBSERVATORIO
A46: 1 | B46: Observatorio | C46: Inteligência de Dados | D46: Marcus Vinícius | E46: Menu Editais Observatório | F46: 44 | G46: Menu_Editais_Observatório | H46: 45482 | I46: 45485 | J46: 24 | K46: Em andamento | L46: 552 | N46: Institucional | O46: Atualização | P46: OBSERVATORIO
A47: 1 | B47: Observatorio | C47: Inteligência de Dados | D47: Diego Gomes | E47: Lista de Empresas do Comércio SENAC | F47: 45 | H47: 45484 | I47: 45484 | J47: 2 | K47: Finalizado | L47: 260 | N47: Institucional | O47: Banco de Dados | P47: SINDICATOS
A48: 1 | B48: Observatorio | C48: Inteligência de Dados | D48: Diego Gomes | E48: Lista de Empresas FIEG - Atualização | F48: 46 | H48: 45485 | I48: 45485 | J48: 4 | K48: Finalizado | L48: 260 | N48: Institucional | O48: Banco de Dados | P48: SINDICATOS
A49: 1 | B49: Observatorio | C49: Inteligência de Dados | D49: Diego Gomes | E49: Painel Inove Mais Digital | F49: 47 | G49: Painel_Inove_Mais_Digital | H49: 45490 | I49: 45504 | J49: 20 | K49: Em andamento | L49: 500 | N49: Institucional | O49: Painel
A50: 1 | B50: Observatorio | C50: Inteligência de Dados | D50: Diego Gomes | E50: Painel dos Sindicados - Diretoria | F50: 48 | G50: Painel_dos_Sindicados_Diretoria | H50: 45490 | I50: 45504 | J50: 60 | K50: Em andamento | L50: 1500 | N50: Institucional | O50: Painel | P50: IEL - SUPERINTENDÊNCIA
A51: 1 | B51: Observatorio | C51: Inteligência de Mercado | D51: Diego Gomes | E51: Painel NPS - Hospitais | F51: 49 | G51: Painel_NPS_Hospitais | H51: 45490 | I51: 45504 | J51: 20 | K51: Em andamento | L51: 500 | N51: Institucional | O51: Painel | P51: IEL - MERCADO
A52: 1 | B52: Observatorio | C52: Inteligência de Mercado | D52: Diego Gomes | E52: Demandas Federação (FIEG, SESI e SENAI) | F52: 50 | G52: Demandas_Federação | H52: 45474 | I52: 45657 | J52: 120 | K52: Em andamento | L52: 5400 | N52: Institucional | O52: Banco de Dados | P52: FIEG
A53: 1 | B53: Observatorio | C53: Inteligência Competitiva | D53: Ely Bastos | E53: Pesquisa - Observatório do Rio Grande do Sul - Construção Civil | F53: 51 | G53: Pesquisa_Observatório_do_Rio_Grande_do_Sul_Construção_Civil | H53: 45505 | I53: 45657 | J53: 92 | K53: Em andamento | L53: 112000 | N53: Mercado | O53: Estudo | P53: MERCADO
A54: 1 | B54: Observatorio | C54: Inteligência Competitiva | D54: Ely Bastos | E54: Pesquisa Idetch | F54: 52 | G54: Pesquisa_Idetch | H54: 45505 | I54: 45657 | K54: Em andamento
A55: 1 | B55: Observatorio | C55: Inteligência de Mercado | D55: Bruno Felipe | E55: Pesquisa Simulador de Entrevista I.A | F55: 53 | H55: 45537 | I55: 45541 | J55: 32 | K55: Em andamento | L55: 1440 | N55: Institucional | O55: Pesquisa | P55: FIEG
A56: 1 | B56: Observatorio | C56: Inteligência de Dados | D56: Diego Gomes | E56: Painel de Governança | F56: 54 | G56: Painel_de_Governança | H56: 45537 | I56: 45555 | K56: Em andamento | N56: Institucional | O56: Painel | P56: OBSERVATORIO
A57: 1 | B57: Observatorio | C57: Inteligência de Dados | D57: Diego Gomes | E57: IFC - Atualização 2024 | F57: 55 | G57: IFC_Atualização2024 | H57: 45536 | I57: 45626 | K57: Em andamento | N57: Institucional | O57: Painel | P57: OBSERVATORIO
A58: 1 | B58: Observatorio | C58: Inteligência de Mercado | D58: Bruno Felipe | E58: Relatório Aprendiz - Evasão | F58: 56 | H58: 45551 | I58: 45555 | J58: 30 | K58: Em andamento | L58: 1050 | N58: Institucional | O58: Painel | P58: OBSERVATORIO
A59: 1 | B59: Observatorio | C59: Inteligência de Mercado | D59: Bruno Felipe | E59: Relatório Prefeituras | F59: 57 | H59: 45572 | I59: 45597 | J59: 400 | K59: Em andamento | L59: 14000 | N59: Institucional | O59: Estudo | P59: IEL - MERCADO

Sheet Tabela Hora x Custo Colaborador
B2: COD | C2: Modelo de Contrato | D2: Colaboradores | E2: Função | F2: Carga horário diária | G2: Carga horário Mensal | H2: Valor Hora (R$)
B3: 1 | C3: CLT | D3: Sandra Marcia | E3: Gerente | F3: 8 | G3: 160 | H3: 150
B4: 2 | C4: CLT | D4: Diego Gomes | E4: Cientista de Dados | F4: 8 | G4: 160 | H4: 65
B5: 3 | C5: CLT | D5: Alexandre Borges | E5: Engenheiro de Dados | F5: 8 | G5: 160 | H5: 55
B6: 4 | C6: Prestador | D6: Rodolfo Viscal | E6: Analista de BI | F6: 8 | G6: 160 | H6: 35
B7: 5 | C7: Prestador | D7: Marcus Vinícius | E7: Estagiário de T.I | F7: 8 | G7: 160 | H7: 35
B8: 6 | C8: CLT | D8: Fernanda Heleno | E8: Analista de Pesquisa | F8: 8 | G8: 160 | H8: 45
B9: 7 | C9: CLT | D9: Ely Bastos | E9: Analista de Relatório | F9: 8 | G9: 160 | H9: 55
B10: 8 | C10: Estagiário | D10: Luis Eduardo | E10: Estagiário de Economia | F10: 6 | G10: 120 | H10: 15
B11: 9 | C11: Estagiário | D11: Nicoly Pacheco | E11: Estagiária de Economia | F11: 6 | G11: 120 | H11: 15
B12: 10 | C12: CLT | D12: Bruno Felipe | E12: Assistente de Dados | F12: 8 | G12: 160 | H12: 25
B13: 11 | C13: Estagiário | D13: Paulo Vinicius | E13: Estagiário de Economia | F13: 6 | G13: 120 | H13: 15
B14: 12 | C14: CLT | D14: Isadora Pereira | E14: Assistente de Projetos | F14: 8 | G14: 160 | H14: 25
... B16: 14 | C16: Estagiário | D16: Antônio Guido | E16: Estagiária de Economia | F16: 6 | G16: 120 | H16: 15

Sheet Classe do Projeto
B2: Classe
B3: Painel
B4: Estudo
B5: Pesquisa
B6: Banco de Dados
B7: Correção
B8: Atualização
B9: Planejamento

Sheet Cliente Final
B2: Cliente Final
B3: FIEG
B4: IEL - PDF
B5: IEL - MERCADO
B6: IEL - APRENDIZ
B7: SINDICATOS
B8: MERCADO
B9: OBSERVATORIO
B10: IEL - SUPERINTENDÊNCIA
B11: SENAI
B12: SESI

Sheet Fontes de Recursos
B2: Fonte do Recurso
B3: Institucional
B4: Mercado

Sheet Status do Projeto
B2: Status
B3: Não Iniciado
B4: Em andamento
B5: Parado
B6: Finalizado

Sheet Áreas da Demanda
B2: Área
B3: Inteligência de Dados
B4: Inteligência Competitiva
B5: Inteligência de Mercado
B6: Gestão

Sheet Etapas Macro
A1: Etapas Macro
A2: Alteração/Ajustes
A3: Estruturação do Projeto
A4: Extração de Dados
A5: Identificação de Indicadores
A6: Painel
A7: Planejamento do Projeto
A8: Relatório
A9: Reunião
A10: Tratamento de Dados
A11: Validação
A12: Coleta
... A21: Monitoramento

Sheet Planilha1
A1: 1 | B1: 2 | C1: 3 | D1: 4 | E1: 5 | F1: 6 | G1: 7 | H1: 8 | I1: 9 | J1: 10 | K1: 11 | L1: 12 | M1: 13 | N1: 14 | O1: 15 | P1: 16 | Q1: 17 | R1: 18 | S1: 19 | T1: 20 | U1: 21 | V1: 22 | W1: O23 | X1: 24 | Y1: 25 | Z1: 26 | AA1: 27 | AB1: 28 | AC1: 29 | AD1: 30 | AE1: 31 | AF1: 32 | AG1: 33 | AH1: 34 | AI1: 35 | AJ1: 36 | AK1: 37 | AL1: 38 | AM1: 39 | AN1: 40 | AO1: 41 | AP1: 42 | AQ1: 43 | AR1: 44 | AS1: 45 | AT1: 46 | AU1: 47 | AV1: 48
A2: Planejamento do Projeto | B2: Planejamento do Projeto | C2: Coleta | D2: Reunião | E2: Reunião | F2: Reunião | G2: Reunião | H2: Reunião | I2: Reunião | J2: Reunião | K2: Reunião | L2: Reunião | M2: Reunião | N2: Reunião | O2: Reunião | P2: Reunião | Q2: Reunião | R2: Estruturação do Projeto | S2: Atualização | T2: Atualização | U2: Atualização | V2: Estruturação do Projeto | W2: Reunião | X2: Reunião | Y2: Reunião | AA2: Planejamento do Projeto | AB2: Planejamento do Projeto | AC2: Planejamento do Projeto | AD2: Reunião | AE2: Reunião | AF2: Capacitação | AG2: Alteração/Ajustes | AH2: Estruturação do Projeto | AJ2: Planejamento do Projeto | AK2: Planejamento do Projeto | AL2: Tratamento de Dados | AM2: Reunião
A3: Extração de Dados | B3: Estruturação do Projeto | C3: Tabulação | D3: Extração de Dados | E3: Extração de Dados | F3: Extração de Dados | G3: Extração de Dados | H3: Extração de Dados | I3: Estruturação do Projeto | J3: Extração de Dados | K3: Estruturação do Projeto | L3: Planejamento do Projeto | M3: Relatório | N3: Estruturação do Projeto | O3: Estruturação do Projeto | P3: Estruturação do Projeto | Q3: Estruturação do Projeto | R3: Alteração/Ajustes | S3: Extração de Dados | T3: Extração de Dados | U3: Extração de Dados | V3: Identificação de Indicadores | W3: Estruturação do Projeto | X3: Extração de Dados | Y3: Alteração/Ajustes | AA3: Identificação de Indicadores | AB3: Identificação de Indicadores | AC3: Identificação de Indicadores | AD3: Estruturação do Projeto | AE3: Relatório | AG3: Atualização | AH3: Relatório | AJ3: Diagnóstico | AK3: Diagnóstico | AL3: Relatório | AM3: Planejamento do Projeto
A4: Tratamento de Dados | B4: Extração de Dados | C4: Relatório | D4: Tratamento de Dados | E4: Tratamento de Dados | F4: Tratamento de Dados | G4: Tratamento de Dados | H4: Tratamento de Dados | I4: Relatório | J4: Tratamento de Dados | K4: Identificação de Indicadores | L4: Identificação de Indicadores | M4: Tratamento de Dados | N4: Identificação de Indicadores | O4: Extração de Dados | P4: Extração de Dados | Q4: Extração de Dados | R4: Extração de Dados | S4: Tratamento de Dados | T4: Tratamento de Dados | U4: Tratamento de Dados | V4: Extração de Dados | W4: Tratamento de Dados | X4: Tratamento de Dados | Y4: Extração de Dados | AA4: Tratamento de Dados | AB4: Tratamento de Dados | AC4: Tratamento de Dados | AD4: Proposta / Contrato | AE4: Atualização | AJ4: Reunião | AK4: Reunião | AL4: Validação | AM4: Proposta / Contrato
A5: Painel | B5: Tratamento de Dados | C5: Alteração/Ajustes | D5: Validação | E5: Validação | F5: Alteração/Ajustes | G5: Validação | H5: Validação | I5: Validação | J5: Relatório | K5: Validação | L5: Extração de Dados | M5: Validação | N5: Extração de Dados | O5: Tratamento de Dados | P5: Tratamento de Dados | Q5: Tratamento de Dados | R5: Tratamento de Dados | S5: Painel | T5: Painel | V5: Tratamento de Dados | W5: Painel | X5: Validação | Y5: Tratamento de Dados | AA5: Relatório | AB5: Relatório | AC5: Relatório | AD5: Extração de Dados | AJ5: Implementação | AK5: Implementação | AM5: Diagnóstico
A6: Alteração/Ajustes | B6: Painel | I6: Alteração/Ajustes | J6: Validação | K6: Extração de Dados | L6: Tratamento de Dados | M6: Alteração/Ajustes | N6: Tratamento de Dados | O6: Relatório | P6: Painel | Q6: Painel | S6: Alteração/Ajustes | T6: Alteração/Ajustes | V6: Painel | W6: Alteração/Ajustes | AA6: Alteração/Ajustes | AB6: Alteração/Ajustes | AC6: Alteração/Ajustes | AJ6: Diagnóstico | AK6: Diagnóstico | AM6: Coleta
B7: Validação | J7: Alteração/Ajustes | K7: Tratamento de Dados | L7: Relatório | N7: Relatório | O7: Validação | P7: Relatório | Q7: Relatório | V7: Validação | AM7: Tabulação
B8: Reunião | K8: Painel | L8: Validação | N8: Painel | O8: Pesquisa | P8: Alteração/Ajustes | Q8: Alteração/Ajustes | V8: Alteração/Ajustes | AM8: Tratamento de Dados
K9: Relatório | N9: Validação | O9: Apresentação/Entrega | AM9: Painel
K10: Alteração/Ajustes | AM10: Relatório
AM11: Validação

Sheet Subetapas do projeto
B2: Nome do Projeto | C2: Cod Projeto | D2: Atividades Macro | E2: Horas Estimadas | F2: Status | I2: Nome do Projeto | J2: Cod Projeto | K2: Atividades | M2: Nome do Projeto | N2: Cod Projeto | O2: Atividades | Q2: Nome do Projeto | R2: Cod Projeto | S2: Atividades | U2: Nome do Projeto | V2: Cod Projeto | W2: Atividades
B3: Atualização de Painel - Educação | C3: =IF(B3<>"",VLOOKUP(B3,Projetos!E:F,2,0),"") -> 1 | D3: Planejamento do Projeto | E3: 6 | F3: Finalizado | I3: Projeto Agrodefesa | J3: 39 | K3: Reunião | M3: Implantação Amazon | N3: 18 | O3: Estruturação do Projeto | Q3: Banco de Dados Mineração | R3: 24 | S3: Reunião | U3: Observatório Nacional | V3: 31 | W3: Reunião
B4: Atualização de Painel - Educação | C4: =IF(B4<>"",VLOOKUP(B4,Projetos!E:F,2,0),"") -> 1 | D4: Extração de Dados | E4: 16 | F4: Finalizado | I4: Projeto Agrodefesa | J4: 39 | K4: Planejamento do Projeto | M4: Implantação Amazon | N4: 18 | O4: Alteração/Ajustes | Q4: Banco de Dados Mineração | R4: 24 | S4: Extração de Dados | U4: Observatório Nacional | V4: 31 | W4: Relatório
B5: Atualização de Painel - Educação | C5: =IF(B5<>"",VLOOKUP(B5,Projetos!E:F,2,0),"") -> 1 | D5: Tratamento de Dados | E5: 16 | F5: Finalizado | I5: Projeto Agrodefesa | J5: 39 | K5: Proposta / Contrato | M5: Implantação Amazon | N5: 18 | O5: Extração de Dados | Q5: Banco de Dados Mineração | R5: 24 | S5: Tratamento de Dados | U5: Observatório Nacional | V5: 31 | W5: Atualização
B6: Atualização de Painel - Educação | C6: =IF(B6<>"",VLOOKUP(B6,Projetos!E:F,2,0),"") -> 1 | D6: Painel | E6: 60 | F6: Finalizado | I6: Projeto Agrodefesa | J6: 39 | K6: Diagnóstico | M6: Implantação Amazon | N6: 18 | O6: Tratamento de Dados | Q6: Banco de Dados Mineração | R6: 24 | S6: Validação
B7: Atualização de Painel - Educação | C7: =IF(B7<>"",VLOOKUP(B7,Projetos!E:F,2,0),"") -> 1 | D7: Alteração/Ajustes | E7: 10 | F7: Finalizado | I7: Projeto Agrodefesa | J7: 39 | K7: Coleta | U7: Nome do Projeto | V7: Cod Projeto | W7: Atividades
B8: Perfil dos Municípios | C8: =IF(B8<>"",VLOOKUP(B8,Projetos!E:F,2,0),"") -> 2 | D8: Planejamento do Projeto | E8: 10 | F8: Finalizado | I8: Projeto Agrodefesa | J8: 39 | K8: Tabulação | M8: Nome do Projeto | N8: Cod Projeto | O8: Atividades | Q8: Nome do Projeto | R8: Cod Projeto | S8: Atividades | U8: Treinamentos e Capacitações | V8: 32 | W8: Capacitação
B9: Perfil dos Municípios | C9: =IF(B9<>"",VLOOKUP(B9,Projetos!E:F,2,0),"") -> 2 | D9: Estruturação do Projeto | E9: 6 | F9: Finalizado | I9: Projeto Agrodefesa | J9: 39 | K9: Tratamento de Dados | M9: MTE - CAGED | N9: 19 | O9: Atualização | Q9: Atualização Painel Mercado | R9: 25 | S9: Reunião
B10: Perfil dos Municípios | C10: =IF(B10<>"",VLOOKUP(B10,Projetos!E:F,2,0),"") -> 2 | D10: Extração de Dados | E10: 170 | F10: Finalizado | I10: Projeto Agrodefesa | J10: 39 | K10: Painel | M10: MTE - CAGED | N10: 19 | O10: Extração de Dados | Q10: Atualização Painel Mercado | R10: 25 | S10: Alteração/Ajustes | U10: Nome do Projeto | V10: Cod Projeto | W10: Atividades
B11: Perfil dos Municípios | C11: =IF(B11<>"",VLOOKUP(B11,Projetos!E:F,2,0),"") -> 2 | D11: Tratamento de Dados | E11: 104 | F11: Finalizado | I11: Projeto Agrodefesa | J11: 39 | K11: Relatório | M11: MTE - CAGED | N11: 19 | O11: Tratamento de Dados | Q11: Atualização Painel Mercado | R11: 25 | S11: Extração de Dados | U11: Painel Institucional - Superintendência | V11: 33 | W11: Alteração/Ajustes
B12: Perfil dos Municípios | C12: =IF(B12<>"",VLOOKUP(B12,Projetos!E:F,2,0),"") -> 2 | D12: Painel | E12: 232 | F12: Finalizado | I12: Projeto Agrodefesa | J12: 39 | K12: Validação | M12: MTE - CAGED | N12: 19 | O12: Painel | Q12: Atualização Painel Mercado | R12: 25 | S12: Tratamento de Dados | U12: Painel Institucional - Superintendência | V12: 33 | W12: Atualização
B13: Perfil dos Municípios | C13: =IF(B13<>"",VLOOKUP(B13,Projetos!E:F,2,0),"") -> 2 | D13: Validação | E13: 6 | F13: Finalizado | M13: MTE - CAGED | N13: 19 | O13: Alteração/Ajustes
B14: PDE - Serra Verde | C14: =IF(B14<>"",VLOOKUP(B14,Projetos!E:F,2,0),"") -> 3 | D14: Reunião | E14: 96 | F14: Em andamento | Q14: Nome do Projeto | R14: Cod Projeto | S14: Atividades | U14: Nome do Projeto | V14: Cod Projeto | W14: Atividades
B15: PDE - Serra Verde | C15: =IF(B15<>"",VLOOKUP(B15,Projetos!E:F,2,0),"") -> 3 | D15: Coleta | E15: 96 | F15: Em andamento | I15: Nome do Projeto | J15: Cod Projeto | K15: Atividades | M15: Nome do Projeto | N15: Cod Projeto | O15: Atividades | Q15: Iniciativas de Mercados - CMs | R15: 27 | S15: Planejamento do Projeto | U15: Gestão do Conhecimento | V15: 36 | W15: Planejamento do Projeto
B16: PDE - Serra Verde | C16: =IF(B16<>"",VLOOKUP(B16,Projetos!E:F,2,0),"") -> 3 | D16: Tabulação | E16: 96 | F16: Em andamento | I16: PDE - Serra Verde | J16: 3 | K16: Reunião | M16: Panorama Econômico | N16: 21 | O16: Atualização | Q16: Iniciativas de Mercados - CMs | R16: 27 | S16: Identificação de Indicadores | U16: Gestão do Conhecimento | V16: 36 | W16: Diagnóstico
B17: PDE - Serra Verde | C17: =IF(B17<>"",VLOOKUP(B17,Projetos!E:F,2,0),"") -> 3 | D17: Relatório | E17: 96 | F17: Em andamento | I17: PDE - Serra Verde | J17: 3 | K17: Coleta | M17: Panorama Econômico | N17: 21 | O17: Extração de Dados | Q17: Iniciativas de Mercados - CMs | R17: 27 | S17: Tratamento de Dados | U17: Gestão do Conhecimento | V17: 36 | W17: Reunião
B18: PDE - Serra Verde | C18: =IF(B18<>"",VLOOKUP(B18,Projetos!E:F,2,0),"") -> 3 | D18: Alteração/Ajustes | E18: 96 | F18: Em andamento | I18: PDE - Serra Verde | J18: 3 | K18: Tabulação | Q18: Iniciativas de Mercados - CMs | R18: 27 | S18: Relatório | U18: Gestão do Conhecimento | V18: 36 | W18: Implementação
B19: Atualização da Base de Dados FIEG | C19: =IF(B19<>"",VLOOKUP(B19,Projetos!E:F,2,0),"") -> 4 | D19: Reunião | E19: 1 | F19: Finalizado | I19: PDE - Serra Verde | J19: 3 | K19: Relatório | M19: Nome do Projeto | N19: Cod Projeto | O19: Atividades | Q19: Iniciativas de Mercados - CMs | R19: 27 | S19: Alteração/Ajustes | U19: Gestão do Conhecimento | V19: 36 | W19: Diagnóstico
B20: Atualização da Base de Dados FIEG | C20: =IF(B20<>"",VLOOKUP(B20,Projetos!E:F,2,0),"") -> 4 | D20: Extração de Dados | E20: 2 | F20: Finalizado | I20: PDE - Serra Verde | J20: 3 | K20: Alteração/Ajustes | M20: Painel de Gestão | N20: 23 | O20: Reunião
B21: Atualização da Base de Dados FIEG | C21: =IF(B21<>"",VLOOKUP(B21,Projetos!E:F,2,0),"") -> 4 | D21: Tratamento de Dados | E21: 3 | F21: Finalizado | M21: Painel de Gestão | N21: 23 | O21: Estruturação do Projeto | U21: Nome do Projeto | V21: Cod Projeto | W21: Atividades
B22: Atualização da Base de Dados FIEG | C22: =IF(B22<>"",VLOOKUP(B22,Projetos!E:F,2,0),"") -> 4 | D22: Validação | E22: 2 | F22: Finalizado | M22: Painel de Gestão | N22: 23 | O22: Tratamento de Dados | Q22: Nome do Projeto | R22: Cod Projeto | S22: Atividades | U22: Gestão de Portfólio | V22: 37 | W22: Planejamento do Projeto
B23: Validação Lista de Empresas - DAIA | C23: =IF(B23<>"",VLOOKUP(B23,Projetos!E:F,2,0),"") -> 5 | D23: Reunião | E23: 1 | F23: Finalizado | I23: Nome do Projeto | J23: Cod Projeto | K23: Atividades | M23: Painel de Gestão | N23: 23 | O23: Painel | Q23: Projetos e Atividades Internas | R23: 30 | S23: Reunião | U23: Gestão de Portfólio | V23: 37 | W23: Diagnóstico
B24: Validação Lista de Empresas - DAIA | C24: =IF(B24<>"",VLOOKUP(B24,Projetos!E:F,2,0),"") -> 5 | D24: Extração de Dados | E24: 1 | F24: Finalizado | I24: Demandas Federação (FIEG, SESI e SENAI) | J24: 50 | K24: Reunião | M24: Painel de Gestão | N24: 23 | O24: Alteração/Ajustes | Q24: Projetos e Atividades Internas | R24: 30 | S24: Estruturação do Projeto | U24: Gestão de Portfólio | V24: 37 | W24: Reunião
B25: Validação Lista de Empresas - DAIA | C25: =IF(B25<>"",VLOOKUP(B25,Projetos!E:F,2,0),"") -> 5 | D25: Tratamento de Dados | E25: 3 | F25: Finalizado | I25: Demandas Federação (FIEG, SESI e SENAI) | J25: 50 | K25: Identificação de Indicadores | Q25: Projetos e Atividades Internas | R25: 30 | S25: Proposta / Contrato | U25: Gestão de Portfólio | V25: 37 | W25: Implementação
B26: Validação Lista de Empresas - DAIA | C26: =IF(B26<>"",VLOOKUP(B26,Projetos!E:F,2,0),"") -> 5 | D26: Validação | E26: 1 | F26: Finalizado | I26: Demandas Federação (FIEG, SESI e SENAI) | J26: 50 | K26: Extração de Dados | Q26: Projetos e Atividades Internas | R26: 30 | S26: Extração de Dados | U26: Gestão de Portfólio | V26: 37 | W26: Alteração/Ajustes
B27: Relatório Rotatividade Farmoquímico | C27: =IF(B27<>"",VLOOKUP(B27,Projetos!E:F,2,0),"") -> 6 | D27: Reunião | E27: 1 | F27: Finalizado | I27: Demandas Federação (FIEG, SESI e SENAI) | J27: 50 | K27: Tratamento de Dados
B28: Relatório Rotatividade Farmoquímico | C28: =IF(B28<>"",VLOOKUP(B28,Projetos!E:F,2,0),"") -> 6 | D28: Extração de Dados | E28: 3 | F28: Finalizado | I28: Demandas Federação (FIEG, SESI e SENAI) | J28: 50 | K28: Painel
B29: Relatório Rotatividade Farmoquímico | C29: =IF(B29<>"",VLOOKUP(B29,Projetos!E:F,2,0),"") -> 6 | D29: Tratamento de Dados | E29: 5 | F29: Finalizado | I29: Demandas Federação (FIEG, SESI e SENAI) | J29: 50 | K29: Proposta / Contrato
B30: Relatório Rotatividade Farmoquímico | C30: =IF(B30<>"",VLOOKUP(B30,Projetos!E:F,2,0),"") -> 6 | D30: Alteração/Ajustes | E30: 2 | F30: Finalizado | I30: Demandas Federação (FIEG, SESI e SENAI) | J30: 50 | K30: Alteração/Ajustes
B31: Relatório Sindmóveis | C31: =IF(B31<>"",VLOOKUP(B31,Projetos!E:F,2,0),"") -> 7 | D31: Reunião | E31: 1 | F31: Finalizado | I31: Demandas Federação (FIEG, SESI e SENAI) | J31: 50 | K31: Apresentação/Entrega
B32: Relatório Sindmóveis | C32: =IF(B32<>"",VLOOKUP(B32,Projetos!E:F,2,0),"") -> 7 | D32: Extração de Dados | E32: 2 | F32: Finalizado
B33: Relatório Sindmóveis | C33: =IF(B33<>"",VLOOKUP(B33,Projetos!E:F,2,0),"") -> 7 | D33: Tratamento de Dados | E33: 1 | F33: Finalizado
B34: Relatório Sindmóveis | C34: =IF(B34<>"",VLOOKUP(B34,Projetos!E:F,2,0),"") -> 7 | D34: Validação | E34: 1 | F34: Finalizado
B35: Lista de Empresas Confecção | C35: =IF(B35<>"",VLOOKUP(B35,Projetos!E:F,2,0),"") -> 8 | D35: Reunião | E35: 1 | F35: Finalizado
B36: Lista de Empresas Confecção | C36: =IF(B36<>"",VLOOKUP(B36,Projetos!E:F,2,0),"") -> 8 | D36: Extração de Dados | E36: 2 | F36: Finalizado
B37: Lista de Empresas Confecção | C37: =IF(B37<>"",VLOOKUP(B37,Projetos!E:F,2,0),"") -> 8 | D37: Tratamento de Dados | E37: 1 | F37: Finalizado
B38: Lista de Empresas Confecção | C38: =IF(B38<>"",VLOOKUP(B38,Projetos!E:F,2,0),"") -> 8 | D38: Validação | E38: 1 | F38: Finalizado
B39: Apresentação Descarbonização da Mineração | C39: =IF(B39<>"",VLOOKUP(B39,Projetos!E:F,2,0),"") -> 9 | D39: Reunião | E39: 2 | F39: Finalizado
B40: Apresentação Descarbonização da Mineração | C40: =IF(B40<>"",VLOOKUP(B40,Projetos!E:F,2,0),"") -> 9 | D40: Estruturação do Projeto | E40: 5 | F40: Finalizado
B41: Apresentação Descarbonização da Mineração | C41: =IF(B41<>"",VLOOKUP(B41,Projetos!E:F,2,0),"") -> 9 | D41: Relatório | E41: 24 | F41: Finalizado
B42: Apresentação Descarbonização da Mineração | C42: =IF(B42<>"",VLOOKUP(B42,Projetos!E:F,2,0),"") -> 9 | D42: Validação | E42: 2 | F42: Finalizado
B43: Apresentação Descarbonização da Mineração | C43: =IF(B43<>"",VLOOKUP(B43,Projetos!E:F,2,0),"") -> 9 | D43: Alteração/Ajustes | E43: 4 | F43: Finalizado
... B177: Relatório Município de Nova Roma | C177: =IF(B177<>"",VLOOKUP(B177,Projetos!E:F,2,0),"") -> 38 | D177: Validação | E177: 1 | F177: Finalizado
B178: Projeto Agrodefesa | C178: =IF(B178<>"",VLOOKUP(B178,Projetos!E:F,2,0),"") -> 39 | D178: Reunião | F178: Em andamento
B179: Projeto Agrodefesa | C179: =IF(B179<>"",VLOOKUP(B179,Projetos!E:F,2,0),"") -> 39 | D179: Planejamento do Projeto | F179: Em andamento
B180: Projeto Agrodefesa | C180: =IF(B180<>"",VLOOKUP(B180,Projetos!E:F,2,0),"") -> 39 | D180: Proposta / Contrato | F180: Em andamento
B181: Projeto Agrodefesa | C181: =IF(B181<>"",VLOOKUP(B181,Projetos!E:F,2,0),"") -> 39 | D181: Diagnóstico | F181: Em andamento
B182: Projeto Agrodefesa | C182: =IF(B182<>"",VLOOKUP(B182,Projetos!E:F,2,0),"") -> 39 | D182: Coleta | F182: Em andamento
B183: Projeto Agrodefesa | C183: =IF(B183<>"",VLOOKUP(B183,Projetos!E:F,2,0),"") -> 39 | D183: Tabulação | F183: Em andamento
B184: Projeto Agrodefesa | C184: =IF(B184<>"",VLOOKUP(B184,Projetos!E:F,2,0),"") -> 39 | D184: Tratamento de Dados | F184: Em andamento
B185: Projeto Agrodefesa | C185: =IF(B185<>"",VLOOKUP(B185,Projetos!E:F,2,0),"") -> 39 | D185: Painel | F185: Em andamento
B186: Projeto Agrodefesa | C186: =IF(B186<>"",VLOOKUP(B186,Projetos!E:F,2,0),"") -> 39 | D186: Relatório | F186: Em andamento
B187: Projeto Agrodefesa | C187: =IF(B187<>"",VLOOKUP(B187,Projetos!E:F,2,0),"") -> 39 | D187: Validação | F187: Em andamento
B188: Menu Editais Observatório | C188: =IF(B188<>"",VLOOKUP(B188,Projetos!E:F,2,0),"") -> 44 | D188: Estruturação do Projeto | E188: 2 | F188: Finalizado
B189: Menu Editais Observatório | C189: =IF(B189<>"",VLOOKUP(B189,Projetos!E:F,2,0),"") -> 44 | D189: Atualização | E189: 8 | F189: Finalizado
B190: Menu Editais Observatório | C190: =IF(B190<>"",VLOOKUP(B190,Projetos!E:F,2,0),"") -> 44 | D190: Alteração/Ajustes | E190: 8 | F190: Finalizado
B191: Menu Editais Observatório | C191: =IF(B191<>"",VLOOKUP(B191,Projetos!E:F,2,0),"") -> 44 | D191: Validação | E191: 6 | F191: Finalizado
B192: Lista de Empresas do Comércio SENAC | C192: =IF(B192<>"",VLOOKUP(B192,Projetos!E:F,2,0),"") -> 45 | D192: Extração de Dados | E192: 1 | F192: Finalizado
B193: Lista de Empresas do Comércio SENAC | C193: =IF(B193<>"",VLOOKUP(B193,Projetos!E:F,2,0),"") -> 45 | D193: Tratamento de Dados | E193: 1 | F193: Finalizado
B194: Lista de Empresas FIEG - Atualização | C194: =IF(B194<>"",VLOOKUP(B194,Projetos!E:F,2,0),"") -> 46 | D194: Extração de Dados | E194: 2 | F194: Finalizado
B195: Lista de Empresas FIEG - Atualização | C195: =IF(B195<>"",VLOOKUP(B195,Projetos!E:F,2,0),"") -> 46 | D195: Tratamento de Dados | E195: 2 | F195: Finalizado
B196: Painel dos Sindicados - Diretoria | C196: =IF(B196<>"",VLOOKUP(B196,Projetos!E:F,2,0),"") -> 48 | D196: Reunião | E196: 10 | F196: Em andamento
B197: Painel dos Sindicados - Diretoria | C197: =IF(B197<>"",VLOOKUP(B197,Projetos!E:F,2,0),"") -> 48 | D197: Painel | E197: 40 | F197: Finalizado
B198: Painel dos Sindicados - Diretoria | C198: =IF(B198<>"",VLOOKUP(B198,Projetos!E:F,2,0),"") -> 48 | D198: Tratamento de Dados | E198: 10 | F198: Finalizado
B199: Painel dos Sindicados - Diretoria | C199: =IF(B199<>"",VLOOKUP(B199,Projetos!E:F,2,0),"") -> 48 | D199: Validação | E199: 6 | F199: Em andamento
... B211: Demandas Federação (FIEG, SESI e SENAI) | C211: =IF(B211<>"",VLOOKUP(B211,Projetos!E:F,2,0),"") -> 50 | D211: Apresentação/Entrega | E211: 10 | F211: Em andamento
B212: Pesquisa - Observatório do Rio Grande do Sul - Construção Civil | C212: =IF(B212<>"",VLOOKUP(B212,Projetos!E:F,2,0),"") -> 51 | D212: Reunião | F212: Em andamento
B213: Relatório Prefeituras | C213: =IF(B213<>"",VLOOKUP(B213,Projetos!E:F,2,0),"") -> 57 | D213: Extração de Dados
B214: Relatório Prefeituras | C214: =IF(B214<>"",VLOOKUP(B214,Projetos!E:F,2,0),"") -> 57 | D214: Tratamento de Dados
B215: Relatório Prefeituras | C215: =IF(B215<>"",VLOOKUP(B215,Projetos!E:F,2,0),"") -> 57 | D215: Estruturação do Projeto
B216: Relatório Prefeituras | C216: =IF(B216<>"",VLOOKUP(B216,Projetos!E:F,2,0),"") -> 57 | D216: Relatório
B217: Relatório Prefeituras | C217: =IF(B217<>"",VLOOKUP(B217,Projetos!E:F,2,0),"") -> 57 | D217: Alteração/Ajustes
C218: =IF(B218<>"",VLOOKUP(B218,Projetos!E:F,2,0),"")
C219: =IF(B219<>"",VLOOKUP(B219,Projetos!E:F,2,0),"")
C220: =IF(B220<>"",VLOOKUP(B220,Projetos!E:F,2,0),"")
C221: =IF(B221<>"",VLOOKUP(B221,Projetos!E:F,2,0),"")
C222: =IF(B222<>"",VLOOKUP(B222,Projetos!E:F,2,0),"")
C223: =IF(B223<>"",VLOOKUP(B223,Projetos!E:F,2,0),"")
C224: =IF(B224<>"",VLOOKUP(B224,Projetos!E:F,2,0),"")
C225: =IF(B225<>"",VLOOKUP(B225,Projetos!E:F,2,0),"")
C226: =IF(B226<>"",VLOOKUP(B226,Projetos!E:F,2,0),"")
C227: =IF(B227<>"",VLOOKUP(B227,Projetos!E:F,2,0),"")
C228: =IF(B228<>"",VLOOKUP(B228,Projetos!E:F,2,0),"")
C229: =IF(B229<>"",VLOOKUP(B229,Projetos!E:F,2,0),"")
C230: =IF(B230<>"",VLOOKUP(B230,Projetos!E:F,2,0),"")
